[
    {
        "name": "",
        "message": "時は少し遡って――。"
    },
    {
        "name": "葛の葉",
        "message": "はじめまして……だね。$n話は聞いていたよ、フェイちゃん"
    },
    {
        "name": "フェイ",
        "message": "お初にお目にかかります、葛の葉様。$n異界から訪れた僕たちを受け入れてくださり、$n感謝いたします"
    },
    {
        "name": "葛の葉",
        "message": "いいや、気にしないでよ。$n異界から来ようが何だろうが、助けを求める人の前に$n陰陽寮の門戸は平等に開かれているからね"
    },
    {
        "name": "葛の葉",
        "message": "それに君とアメちゃんは、ただ助けを求めに来た$nわけじゃない。こちらの世界の危機について$n伝えに来てくれた……そうだろう？"
    },
    {
        "name": "アメ",
        "message": "当機とフェイがいた場所、龍城境は、$n歴史の流れから外れた場所。$n本流から切り離され、別の歴史を歩んだ場所だった"
    },
    {
        "name": "アメ",
        "message": "龍城境の住人は、長らく島の外を知らなかった。$n「嵐の壁」と呼ばれる不可侵の領域が、外界との往来を$n拒む壁となって悠久の断絶を生んでいたのだ"
    },
    {
        "name": "フェイ",
        "message": "あの壁は僕たちの祖先、古のハイレン達の選択でした。$n彼らは海の向こうに何か“恐ろしいもの”を見て、$nそれから身を守るために自分たちの世界を閉ざした……"
    },
    {
        "name": "アメ",
        "message": "だが、それだけではハイレンに未来はない。$n我々は<name></name>たちの協力の下、$nその壁を取り払ったのだ"
    },
    {
        "name": "フェイ",
        "message": "壁を取り払ったことによって、僕たちは海の外、$n世界の向こう側につながることができました。$n僕の目標はその“向こう側”を知ることだったんですが"
    },
    {
        "name": "ヒナモリ",
        "message": "いつの間にかあの街、$nセーガクシティに流れ着いていたと"
    },
    {
        "name": "フェイ",
        "message": "うん。多分だけど、あの場所は“外側の世界”の末端……$n“外側”とは大本が同じで、いわば幹と枝葉の関係。$nそういう部分に、僕たちは迷い込んでいたんだと思う"
    },
    {
        "name": "ヒナモリ",
        "message": "外側の世界……。$nええ、間違いないでしょう"
    },
    {
        "name": "葛の葉",
        "message": "……フェイちゃん。$n陰陽寮側の見解と突き合わさせてもらっていいかな？"
    },
    {
        "name": "葛の葉",
        "message": "フェイちゃんの住んでいる龍城境もそうだけど、$nそれとは別にこの世界も、$n“外の世界”から来た者の侵略を受けていてね"
    },
    {
        "name": "葛の葉",
        "message": "これ自体は<name></name>君たちの$nおかげで退けることはできたけど、$nこの件で厄介な問題が表面化したんだよ"
    },
    {
        "name": "葛の葉",
        "message": "どうやら今の私たちがいるこの世界自体が、$n“つながりやすく”なっているみたいなんだ"
    },
    {
        "name": "葛の葉",
        "message": "実はね。今と似たような状況は以前にも起きて$nいたんだ。1000年前の災厄が起きた時だよ"
    },
    {
        "name": "葛の葉",
        "message": "あの時、私の故郷のイツクサを始めとして、$n大陸中の至るところが瘴気に呑まれ、$n地上から消滅していったんだ"
    },
    {
        "name": "葛の葉",
        "message": "あれは災厄に合わせて“外の世界”に$nつながっていたんじゃないかな？$n1000年に一度、地上から土地が消えていくんだ"
    },
    {
        "name": "フェイ",
        "message": "龍城境が地上から消えたのは2000年ほど前、$n神代の終わり頃の話です。$n周期としては災厄と一致しますね"
    },
    {
        "name": "葛の葉",
        "message": "もしこの仮説が正しいなら、$n災厄を退けたとしても危機は残ったままだ。$nもし、つながりやすくなったままだとしたら……"
    },
    {
        "name": "フェイ",
        "message": "先日の侵略だけにとどまらず、$nその状態に付け込もうとする者が現れる……$nそういうことですよね？"
    },
    {
        "name": "葛の葉",
        "message": "……話が早くて助かるよ。$n侵略を企む存在が妲己だけだとは、$n私にはどうしても思えなくてね"
    },
    {
        "name": "ヒナモリ",
        "message": "そしてその疑念は確信になりました。$n私たちが遭遇した、あの殺生石――"
    },
    {
        "name": "ヒナモリ",
        "message": "あれ自体はすでに討伐済みですが、$n戦闘時の霊力を解析し、とある戦闘記録と$n照合してみたんです。そして、一つの結論を得ました"
    },
    {
        "name": "ヒナモリ",
        "message": "<name></name>さんたちが遭遇した$n千年狐狸精と、殺生石は、おそらく源流を同じく$nするもの……そしてそれが枝分かれしたものです"
    },
    {
        "name": "フェイ",
        "message": "……！　千年狐狸精って、$n別の世界のマガツヒの王だって話でしたよね……？$nそれじゃあ、僕たちが戦った相手も……？"
    },
    {
        "name": "ミカ",
        "message": "なぁに？$nあの狐狸精のこと？"
    },
    {
        "name": "ミカ",
        "message": "あんまり私から言いたいことじゃないけど……$nアレはたぶん“マガツヒの王そのものじゃない”と思う"
    },
    {
        "name": "ミカ",
        "message": "理由……？$nなんとなく分かるの。“同類の匂い”ってやつが"
    },
    {
        "name": "ミカ",
        "message": "ヨモツオオカミを本体とするなら、私たちは$nそこから生じた“別のマガツヒの王”だった。$n力の源流は同じだけれど、力の大きさは劣る"
    },
    {
        "name": "ミカ",
        "message": "狐狸精はたぶんそういうやつ。$n本物だけど本物じゃないって感じかな？"
    },
    {
        "name": "ミカ",
        "message": "で、殺生石たちは“王の力を受けた存在”、$nマガツノミコやヨモツイクサに相当するものね"
    },
    {
        "name": "ミカ",
        "message": "何が言いたいかって？"
    },
    {
        "name": "ミカ",
        "message": "“まだいるかもしれない”ってことだよ。$nこっちに干渉してくる、マガツヒの王の力を持った$n誰かが"
    },
    {
        "name": "ヒナモリ",
        "message": "大陸の各地に瘴気溜まりが相次いで発生しています。$n今は対処できる規模に収まってはいますが……"
    },
    {
        "name": "ヒナモリ",
        "message": "いずれ、ヨモツオオカミがやろうとしたような、$nあちら側とこの世界が反転してしまうような事態が$n起こらないとも限らない。危機は去っていないんです"
    },
    {
        "name": "葛の葉",
        "message": "君たち龍城境の民に協力を依頼したのは、$nそうした経緯からだ"
    },
    {
        "name": "ヒナモリ",
        "message": "嵐の壁が無くなった後の龍城境は、$n外の世界からの脅威に晒されています。$n私たち陰陽寮はその脅威への対抗手段を提供し……"
    },
    {
        "name": "フェイ",
        "message": "僕たちは、龍城境の外の世界を探索して得た情報を$n陰陽寮に提供し、何らかの異常を発見した場合は$n即座に連携できるようにする……でしたよね？"
    },
    {
        "name": "フェイ",
        "message": "もちろんやらせてください。$n外界の探索はもともとやっていたことですし、$n援助もありがたいです。何より――"
    },
    {
        "name": "フェイ",
        "message": "あなたたち陰陽寮には大恩があります。$n僕はその恩義に報いたい"
    },
    {
        "name": "ヒナモリ",
        "message": "それがひと月前のこと……。$nそして先日、フェイさんたちの消息が途絶えました"
    },
    {
        "name": "壱与",
        "message": "命にべつじょーがないのは予のじゅつで確認している。$nだが、連絡がとだえた先がすこし厄介でな……"
    },
    {
        "name": "イズナ",
        "message": "龍城境の海の向こうなのだろう？$nその言い方だと、漂流……というわけではなさそうだな"
    },
    {
        "name": "ヒナモリ",
        "message": "龍城境は隔離された世界です。$nあの海も、途中までは普通の海ですが、$n一定の領域を超えると概念的なものに変わります"
    },
    {
        "name": "ヒナモリ",
        "message": "それより先は普通の航海術で渡ることができない場所。$n見かけ上は海ですが、実態は黄泉比良坂などに近い、$nいわば世界の狭間のようなものなのです"
    },
    {
        "name": "壱与",
        "message": "世界のはざまに、龍城境のような世界が$n浮島のようにいくつかうかんでいると$nおもってもらえばいい"
    },
    {
        "name": "イズナ",
        "message": "ふぅむ……$n浮島のように浮かぶ無数の世界、か……。$nとなると、フェイはその中のどこかに？"
    },
    {
        "name": "ヒナモリ",
        "message": "ええ。場所は分かっています。$n失踪する直前に、フェイさんから連絡が$nありましたから"
    },
    {
        "name": "壱与",
        "message": "おまえたちにはその場所にむかってもらうつもりだ。$nくだんの場所が異界にあるため、$nとつにゅーできる人間の数はかぎられてくるのだが……"
    },
    {
        "name": "ヒナモリ",
        "message": "人数の選定と鬼道での保護は私たちで行います。$nあなたたちはすぐに出発の準備を整えてください"
    },
    {
        "name": "ヒナモリ",
        "message": "行き先は遥か昔、$n地図から一夜にして消えた幻の国……$n「大邑」です……！！"
    },
    {
        "name": "ヤクシニ",
        "message": "大邑って……それ、<name></name>が$n戦った、妲己ってやつがいた所なんじゃないの……！？$nなんでまたその名前が出てくるのさ……？"
    },
    {
        "name": "アスカ",
        "message": "その妲己が実は生きてて、$nご主人たちに復讐しようとしてる……とか？"
    },
    {
        "name": "",
        "message": "妲己は確かに自分たちの目の前で消滅したはず……。$nとても生きているようには思えないが……。"
    },
    {
        "name": "イズナ",
        "message": "ミカやキクリヒメも同じ見解だった。$nその点も不可解ではあるが、$nその前に一つ訂正しておくことがある"
    },
    {
        "name": "イズナ",
        "message": "<name></name>たちがやつと戦った場所は、$n大邑そのものではないということだ。あれはミカを$nおびき出すためにやつが作ったものだったのだ"
    },
    {
        "name": "ヤクシニ",
        "message": "ああ、そうだったね。$n妲己がいた大邑は……もう人間が$n完全に滅んだ後……だっけ？"
    },
    {
        "name": "アスカ",
        "message": "ってなると、フェイちゃんは誰もいない大邑に$n一人で捕まっちゃってるってことっスか？"
    },
    {
        "name": "ヤクシニ",
        "message": "そういうことになるだろうね……。$n人間が滅びた後の土地だなんて、どんな過酷な$n環境になってるのか想像もつかないけど……"
    },
    {
        "name": "アメ",
        "message": "いや、おそらく“そうはなっていない”"
    },
    {
        "name": "",
        "message": "アメ？　船の航行は問題ないのだろうか？"
    },
    {
        "name": "アメ",
        "message": "この船は当機の権能で顕現させているものだ。$nここにいても外の状況は知覚できている。$n当機がここにいても問題はない"
    },
    {
        "name": "アメ",
        "message": "それよりも先程の話だ。$n今から向かう大邑は、「妲己が話していた大邑」とは$n異なるものだろうと推測している"
    },
    {
        "name": "アスカ",
        "message": "え？　違うんスか！？$nでも、なんでそんなこと分かるんスか？"
    },
    {
        "name": "アメ",
        "message": "当機とフェイでいくつかの世界を回ってみての勘だ。$nその妲己という者の世界は“離れすぎている”"
    },
    {
        "name": "ヤクシニ",
        "message": "離れすぎ……？$nどういうこと？"
    },
    {
        "name": "アメ",
        "message": "外側の世界のうち、我々の世界からたどり着けるのは、$n“何かが少しだけ違う場所”、$nつまり、諸々の条件がほぼ同じ場所だ"
    },
    {
        "name": "アメ",
        "message": "極端な話をするのであれば、$n「人類の代わりにタコ人間が地上に栄えている」……$nといった世界があったとしても、我々はたどり着けない"
    },
    {
        "name": "アスカ",
        "message": "本当に極端な例えっスね……"
    },
    {
        "name": "アメ",
        "message": "妲己の世界は、それくらい$nかけ離れていたということだ"
    },
    {
        "name": "アメ",
        "message": "やつはマガツヒの王と深く結びついていたし、$n地上はすでに人が死に絶えている状態だった。$nもはやそれは“人間の住む世界”とは言えないだろう"
    },
    {
        "name": "アメ",
        "message": "故にやつはこの世界に干渉する手段として、ミカに$n目を付けたのだ。やつの世界とこちらをつなぐには、$n近い存在であるミカを経由しなくてはならなかった"
    },
    {
        "name": "妲己",
        "message": "この場所は外なる世界に連なる場所。$n空間や時を超えて、可能性が交わる場所"
    },
    {
        "name": "妲己",
        "message": "つまり、あなたたちの知る世界とは$n別の世界が交わる可能性もある。$nその考えには至らなかったのですか？"
    },
    {
        "name": "",
        "message": "自分たちが遭遇した妲己もそのような話をしていた。$nあの大邑は、別の世界の大邑が交わったものだと。"
    },
    {
        "name": "アスカ",
        "message": "別の世界の大邑……。$nあれ？　じゃあ私たちが向かってる大邑は何なんスか？"
    },
    {
        "name": "アメ",
        "message": "我々の世界の大邑から派生したものだと推測している。$n妲己と仙人達の抗争の末に、地上から消えた幻の国……$n詳しい内情は分からないな"
    },
    {
        "name": "ヤクシニ",
        "message": "つまるところ“出たとこ勝負”ってワケかぁ～……。$nオマケに侵入できる人数に限りがあるなんてさ"
    },
    {
        "name": "アメ",
        "message": "謝罪。それは世界の性質と当機の限界ゆえだ。$n先述した通り、外側の世界と我々の世界との乖離が$n大きいと、我々は干渉することができなくなる"
    },
    {
        "name": "アメ",
        "message": "それはこの船に同乗する人員の性質に左右される。$n大邑と縁が薄い者が増えすぎると、針路が$n目的地の座標からずれて、そもそも侵入が不可能になる"
    },
    {
        "name": "ヤクシニ",
        "message": "それでボクたちが選ばれたんだっけ。$n大邑は仙人と縁の深い国だったから"
    },
    {
        "name": "アメ",
        "message": "ああ、貴殿らであれば座標のズレが少なくて済む。$n戦闘能力、ならびにこの任務に必要となる探索能力も$n申し分ない――"
    },
    {
        "name": "太上老君",
        "message": "むっふっふっふっふ！！$n分かっておるではないか……！！$nわちの実力を頼りにしておるとはのう……！"
    },
    {
        "name": "ヤクシニ＆イズナ",
        "message": "………………"
    },
    {
        "name": "太上老君",
        "message": "まあ、わちって偉大な神仙じゃしなぁ！$nおまけにむちむちうれうれで、$n大人の魅力も兼ね備えていると来ている……！"
    },
    {
        "name": "太上老君",
        "message": "わちが呼ばれた時点で今回の件は$n解決したも同然じゃな！　文字通り、$n大船に乗ったつもりでいてもらってよいぞ！"
    },
    {
        "name": "イズナ",
        "message": "はぁ～～……太上老君かぁ～……。$n河伯か白澤が良かったんだがなぁ～……"
    },
    {
        "name": "ヤクシニ",
        "message": "師匠じゃ何かあった時の戦力としては心許ないよねぇ。$n白澤先生とかなら、その点は安心だったんだけど"
    },
    {
        "name": "太上老君",
        "message": "うぉい！！　失礼じゃぞ其方たち！！$n「太上老君さんが来てくれてありがたい」と$n泣いて喜ぶところじゃろう！"
    },
    {
        "name": "アスカ",
        "message": "まあまあ！　たしかに太上老君ちゃんはにぎやかしに$nしかなってないっスけど、向こうの船室には戦力に$nなってくれそうな式神の皆さんが控えてるっスから！"
    },
    {
        "name": "太上老君",
        "message": "ぬぁっ！！？　完全にわち以外の者たちに$n期待が集まっておる！？　おい、ナタク！$nもう一人の弟子としてわちを持ち上げるのじゃ――"
    },
    {
        "name": "太上老君",
        "message": "ん……？　ナタク、どうした？$n反応が薄いようじゃが……？"
    },
    {
        "name": "ナタク",
        "message": "すぴ～～～～～～～……"
    },
    {
        "name": "太上老君",
        "message": "凛々しい顔のまま寝ておる！！？"
    },
    {
        "name": "ヤクシニ",
        "message": "ナタクは難しい話になるといつもこうなんだ。$n途中まで頑張って聞こうとしてたけど、$n睡魔に勝てなかったみたいだね"
    },
    {
        "name": "太上老君",
        "message": "ぐぬぬ……そういえば日頃わちが講義を$nしてやってる時もこんな感じじゃった……"
    },
    {
        "name": "ナギ",
        "message": "まあまあ、老君ちゃん、落ち着いて？$n老君ちゃんの好きなおぜんざい作ってあげようか？"
    },
    {
        "name": "太上老君",
        "message": "まことか！？$nお餅はマシマシにしてくれるんじゃろうな！？"
    },
    {
        "name": "イズナ",
        "message": "あ！　ずるいぞ！$nナギ、私の分はモナカも入れてくれ！"
    },
    {
        "name": "",
        "message": "こんな調子で良いのだろうか……？$n今から敵の拠点かもしれない場所に$n乗り込むというのに……。"
    },
    {
        "name": "アメ",
        "message": "気にすることはない。どのみち到着してからは$n嫌でも気を張らないといけないのだ。$n今くらいは息抜きも必要だろう"
    },
    {
        "name": "アメ",
        "message": "この天磐船(あめのいわふね)は、同乗者たちの$n霊力を借りて、権能を補って顕現させているものだ。$n乗っているだけでも貴殿らはわずかに力を消耗している"
    },
    {
        "name": "アメ",
        "message": "ならばできるだけ休んでおくのが良いだろう？$n警戒はこちらで行っている。$n何かあれば即座に対応できる"
    },
    {
        "name": "",
        "message": "そうか。$nそういうことならば自分も休ませてもらうとしよう。"
    },
    {
        "name": "",
        "message": "その備えは正しい。マガツヒやケガレ、$n“彼らがこれまでに遭遇してきた敵”を想定した$nものならば、対策としては十分すぎるくらいだ。"
    },
    {
        "name": "",
        "message": "けれど彼らは分かっていない。$n彼らが挑もうとしている者が$n“これまでの常識の外”にあるものだということを。"
    },
    {
        "name": "アメ",
        "message": "…………！？$n何だ……！？　障壁が……！？"
    },
    {
        "name": "ナタク",
        "message": "アメ……！！$n伏せろ……！！"
    },
    {
        "name": "アメ",
        "message": "理解不能……！$nいつの間に内部にまで入り込まれていた……！？$nそんな兆候は微塵もなかったはず――"
    },
    {
        "name": "ヤクシニ",
        "message": "理由を考えてる場合じゃないよ！$nこれだけの数、すぐに対処しないと船が――！！"
    },
    {
        "name": "太上老君",
        "message": "…………！！$n違うぞ、ヤクシニ……！$n対処すべきは目の前の敵ではない……！"
    },
    {
        "name": "ヤクシニ",
        "message": "なっ……！？$n何が起きて……！？"
    },
    {
        "name": "アメ",
        "message": "ぐっ……そ、そんな……"
    },
    {
        "name": "アメ",
        "message": "こいつら……権能を食い荒らしている……。$nこれでは……船の維持が……"
    },
    {
        "name": "イズナ",
        "message": "マズい……！$n近くの物に掴まれ！　船が落ちるぞ！！"
    },
    {
        "name": "",
        "message": "常識の外の世界、常識の外の敵。$nこれは、まあ「手荒い歓迎」とでも受け止めることだ。"
    },
    {
        "name": "",
        "message": "これを乗り越えられないなら、どのみち先はない。$nけれどもし、運と能力、それに$nほんの少しの縁に恵まれていたとすれば……"
    },
    {
        "name": "",
        "message": "何かが届くかもしれない。$n世界の外側のこの場所に。"
    },
    {
        "name": "",
        "message": "何が起きている……？$nこの少女が自分を助けてくれたのか……？"
    },
    {
        "name": "？？？",
        "message": "ん？　何？$nボクの愛らしい顔に見とれちゃった？"
    },
    {
        "name": "",
        "message": "え……！？$nい、いや、そういうわけでは……！？"
    },
    {
        "name": "？？？",
        "message": "あはは！　照れなくてもいいって！$nようやく会えたんだもの。時間を忘れて$n愛しいボクと語り合いたいのも無理からぬことだ"
    },
    {
        "name": "",
        "message": "やたらと自己肯定感が高い……！？$nいや、それよりも今「ようやく会えた」と$n言っていたのは――"
    },
    {
        "name": "ロァン",
        "message": "ずいぶんと余裕のある口ぶりだな。$n自分の状況が分かっていないのか？"
    },
    {
        "name": "獣人たち",
        "message": "たった一度しのいだだけだ！$nその程度でいい気になるなよ？"
    },
    {
        "name": "",
        "message": "マズい！　この少女が何者かは分からないが、$nいくら何でも多勢に無勢だ……！$n状況が危機的なことに変わりはない……！"
    },
    {
        "name": "ロァン",
        "message": "貴様、見たところ我々に近い存在だな？$nなぜ人間の肩を持つのかは知らんが……"
    },
    {
        "name": "ロァン",
        "message": "その男を置いてすぐに失せろ。$nそうすれば手痛い傷を負わずに済むぞ？"
    },
    {
        "name": "？？？",
        "message": "はっ……！$n獣仙ってのは冗談が下手だね？"
    },
    {
        "name": "？？？",
        "message": "要求するのはこっちの方だ。$n今なら半殺しで済ませてやるからとっとと失せな"
    },
    {
        "name": "獣人たち",
        "message": "舐めやがって、この野郎っっ！！！！"
    },
    {
        "name": "？？？",
        "message": "おお、気が短いね。$n怖いったらありゃしない"
    },
    {
        "name": "",
        "message": "逃げろ……！　このままでは……！！"
    },
    {
        "name": "？？？",
        "message": "大丈夫だよ。$nこいつらには……そうだな……"
    },
    {
        "name": "？？？",
        "message": "三日もあれば足りるか"
    },
    {
        "name": "？？？",
        "message": "青陽滌沙-三天哭-"
    },
    {
        "name": "獣人たち",
        "message": "ぐおおおおおおっ！！！？"
    },
    {
        "name": "ロァン",
        "message": "ちっ……！$n土剋……牢磐堰水！！"
    },
    {
        "name": "？？？",
        "message": "やっぱり、師父級の相手は耐えてくるか。$n<name></name>、ボクの手を！　逃げるよ！"
    },
    {
        "name": "？？？",
        "message": "よし……と。$n痕跡も消しておいたから、$n獣仙の鼻でも追跡できないはずだ"
    },
    {
        "name": "",
        "message": "近くに人の気配もない……。$nしばらくは大丈夫そうだが……。"
    },
    {
        "name": "",
        "message": "改めて教えてほしい。$n君は何者で、なぜ自分を助けてくれたのか。$n自分のことを知っているようだが……？"
    },
    {
        "name": "？？？",
        "message": "ああ、そうだね。$nようやく語らう時間もできたことだし"
    },
    {
        "name": "？？？",
        "message": "いいかい？　ここはキミたちの世界から少しだけ$n外れた場所。ということはキミたちと同じ世界の者が$n紛れ込んでいても不思議はないだろう？"
    },
    {
        "name": "キノエ",
        "message": "自己紹介しよう。$nボクはキノエ。$n四獣が一にして、親愛なるキミの協力者さ"
    }
]