[
    {
        "name": "弁財天",
        "message": "……ソレと、二人で話がしたいの"
    },
    {
        "name": "",
        "message": "鬼貌牢(きぼうろう)での一件からしばらくして。$n見舞いに来た弁財天は、毘沙門天を指差して$nそんなことを言い出した。"
    },
    {
        "name": "毘沙門天",
        "message": "ふふ……どうしたの、そんな顔をして。$n顔中真っ青よ。具合でも悪いの？"
    },
    {
        "name": "弁財天",
        "message": "あんたには言ってない！"
    },
    {
        "name": "弁財天",
        "message": "陰陽師君、いいでしょ？　ちょっとコレ、借りるから"
    },
    {
        "name": "",
        "message": "弁財天の剣幕に面食らうが、同じ七福同士、$n何か積もる話でもあるのだろう。$n承諾して、部屋を出る二人を見送る。"
    },
    {
        "name": "毘沙門天",
        "message": "ふふ、久しぶりね、テンテン？$n元気してた？"
    },
    {
        "name": "弁財天",
        "message": "あんたにだけはその名前で呼ばれたくないわ！$n一体どういうつもりよ！"
    },
    {
        "name": "毘沙門天",
        "message": "やぁねぇ、カリカリしちゃって。$nたかがちっぽけな牢屋を出たくらいで、$nそんなに怒らないでよ"
    },
    {
        "name": "弁財天",
        "message": "「たかが」ですって……！？$n災いの化身、十二天が野放しになってるなんて、$nそんな事態……許されるわけないでしょう！"
    },
    {
        "name": "毘沙門天",
        "message": "あら？　わたしを“肉袋”に封じ込めて、$n「毘沙門天」なんて名前でわたしの「業」を縛って……$nそれでもまだ、不安なようね？　ふふふ……"
    },
    {
        "name": "毘沙門天",
        "message": "まぁそこまでしても、わたしは抑えられないのだけど。$nわたしが牢屋にいてあげたのは、ただの気まぐれ。$nその気になればいつでも出られたのよ？"
    },
    {
        "name": "弁財天",
        "message": "……ならもう一度、いえ、何度だって、$nあの監獄に放り込んであげるわ！"
    },
    {
        "name": "毘沙門天",
        "message": "ふふ……威勢のいいこと。$nでも、これを見ても同じことを言えるかしら？"
    },
    {
        "name": "毘沙門天",
        "message": "あなたのお気に入りの、<name></name>君。$nあの子、とってもカワイイわよね"
    },
    {
        "name": "弁財天",
        "message": "それ……呪符……っ！？$n彼に何をしたの！！"
    },
    {
        "name": "毘沙門天",
        "message": "これ、割符になっているの。$n片割れの方は……彼の心臓に貼り付けてあるわ"
    },
    {
        "name": "毘沙門天",
        "message": "わたしが霊力を込めた瞬間……$n彼の心臓は、地に落ちたザクロみたいに……"
    },
    {
        "name": "弁財天",
        "message": "…………何が望みなの？$n閉じ込めてたことへの復讐？"
    },
    {
        "name": "毘沙門天",
        "message": "あははっ！$n別に、復讐なんかじゃないわぁ。$nわたし、ぜ～んぜん恨んでないもの"
    },
    {
        "name": "毘沙門天",
        "message": "わたしはただ……$nあなたの“その顔”が見たかっただけ。$nと～っても、カワイイわよ……ふふ…………"
    },
    {
        "name": "弁財天",
        "message": "…………っ！！"
    },
    {
        "name": "毘沙門天",
        "message": "ふぅん……あなただったら、飛びかかってでも$nこの符を奪いにくると思ってたんだけど"
    },
    {
        "name": "毘沙門天",
        "message": "拳を握って、歯を食いしばって、$nそんなに苦しそうな顔なのに動けないなんて……$nあなた、そんなにわたしが怖いのかしら？"
    },
    {
        "name": "毘沙門天",
        "message": "そうでしょうね。災禍そのものであるわたしを、$n六人がかりでようやく封印できたんだもの。$n一人ではきっと犬死にする。だから――"
    },
    {
        "name": "弁財天",
        "message": "……あたしが死ぬのなんて怖くない。$nあたしは――"
    },
    {
        "name": "弁財天",
        "message": "……いえ。$nあんたに言っても分からないでしょうね"
    },
    {
        "name": "",
        "message": "何やら剣呑な話し声が聞こえた気がするが……$n二人とも、大丈夫だろうか？"
    },
    {
        "name": "毘沙門天",
        "message": "ええ、終わったわ。$n昔話に花が咲いちゃってね"
    },
    {
        "name": "弁財天",
        "message": "あんた、話はまだ――"
    },
    {
        "name": "毘沙門天",
        "message": "ふふ……いいの、テンテン？"
    },
    {
        "name": "弁財天",
        "message": "…………ッ！！"
    },
    {
        "name": "",
        "message": "毘沙門天が指先で何かの符をちらつかせると、$n弁財天は恐ろしい形相で口をつぐんだ。$nその符は一体……？"
    },
    {
        "name": "毘沙門天",
        "message": "君は知らなくていいわ"
    },
    {
        "name": "毘沙門天",
        "message": "テンテンも、“大変なこと”になる前に$nここから消えてちょうだい"
    },
    {
        "name": "弁財天",
        "message": "……あんたを肉の器に封じたのは、$n単に力を制限するためだけではないわ"
    },
    {
        "name": "弁財天",
        "message": "精神は肉体の影響を受ける。$n人の身体を得たことで、もしかしたら、あんたも……"
    },
    {
        "name": "毘沙門天",
        "message": "…………？$n何の話をしているの？"
    },
    {
        "name": "弁財天",
        "message": "何もかもあんたの思うようには行かないってこと"
    },
    {
        "name": "弁財天",
        "message": "それじゃ、失礼するわ"
    },
    {
        "name": "弁財天",
        "message": "……陰陽師君、ごめん。$nあたしたちは無理だったけど……$nでも……あんたなら……"
    },
    {
        "name": "",
        "message": "意味深なつぶやきを残して、$n弁財天は去っていった。"
    },
    {
        "name": "",
        "message": "だが、その瞳は切なる思いを宿しているように見え、 $nいつまでも心の中で引っかかり続けるのだった……。"
    },
    {
        "name": "毘沙門天",
        "message": "はぁ……まったく、手応えがないわね。$nわたしにろくな傷もつけられないなんて"
    },
    {
        "name": "",
        "message": "……しばらくの休養の後、任務に復帰して以来、$nしばしば毘沙門天の力を借りるようになっていた。"
    },
    {
        "name": "",
        "message": "さすが七福だけあって、彼女の力は申し分ないのだが、$n彼女は自身を顧みない戦法ばかり取っている。$nもっと仲間と連携してはどうだろうか？"
    },
    {
        "name": "毘沙門天",
        "message": "マガツヒなんて、わたし一人で片がつくわ。$nわたしは君たちより、ずぅっと強いの。$n協力する必要があると思う？"
    },
    {
        "name": "",
        "message": "しかし、だからといって、$n攻撃をすべて受け止めているのは心配だ。$nもっと自分たちを頼っても……。"
    },
    {
        "name": "毘沙門天",
        "message": "あは。お構いなく。$nその方がわたしの都合がいいのよ"
    },
    {
        "name": "毘沙門天",
        "message": "それにしても、<name></name>君……$n圧倒的強者の心配をするなんて……$nずいぶんと身の程知らずなのねぇ？"
    },
    {
        "name": "",
        "message": "……？$n心配するのに、強い弱いが関係あるだろうか？"
    },
    {
        "name": "毘沙門天",
        "message": "ふふ……君の式神は、$n聞き分けのいい子揃いなのね。$nでもそんな相手ばかりだと思ったら大間違いよ"
    },
    {
        "name": "",
        "message": "そうつぶやいて、彼女は懐から符を取り出す。$n……先日、弁財天に見せていたものと同じ符だ。"
    },
    {
        "name": "毘沙門天",
        "message": "もしかしたら……相手の気まぐれで……$n君なんて、簡単に……ふふふ……"
    },
    {
        "name": "",
        "message": "……っ！？　急に胸が、苦しく……！？$n呼吸もままならず、毘沙門天の足元に$n膝をついてへたり込んでしまう。"
    },
    {
        "name": "毘沙門天",
        "message": "あら、大丈夫？$n任務で疲れてしまったのかしらねぇ……？"
    },
    {
        "name": "",
        "message": "彼女が符をしまうと、途端に胸の不快感は消え去った。$n訳が分からず混乱していると、$n彼女が満面の笑みでのぞき込んでくる。"
    },
    {
        "name": "毘沙門天",
        "message": "君はマガツヒだけでなく、式神にも気をつけることね。$nすぐ隣の“仲間”が、君の心臓を握っているかも$nしれないのだから……ふふふ……"
    },
    {
        "name": "",
        "message": "……彼女の言いたいことはよく分からないが、$nしかし、自分の態度はきっと変わらない。"
    },
    {
        "name": "毘沙門天",
        "message": "…………ふぅん？"
    },
    {
        "name": "",
        "message": "式神と陰陽師は一心同体。$n式神が倒れる時は、陰陽師も共に倒れる時。$n自分の心臓は、いつだって仲間に預けている。"
    },
    {
        "name": "",
        "message": "その思いは、毘沙門天に対しても同じだ。$n毘沙門天が倒れそうな時は、$n自分が命を懸けて毘沙門天を守る。"
    },
    {
        "name": "毘沙門天",
        "message": "……そんなことではないのだけれど"
    },
    {
        "name": "毘沙門天",
        "message": "はぁ……まぁ、いいわ"
    },
    {
        "name": "",
        "message": "不意に背を向けて、毘沙門天は行ってしまった。"
    },
    {
        "name": "マガツヒ",
        "message": "――――――！！！"
    },
    {
        "name": "",
        "message": "――毘沙門天と話した数日後。$nマガツヒが多数出没しているという村へ$n調査に赴いた、のだが……。"
    },
    {
        "name": "イズナ",
        "message": "ぐっ……！！$n負傷者と子供が優先だ、急げ！！$nアスカ、アレを止められんか！！"
    },
    {
        "name": "アスカ",
        "message": "む、無茶振りっスよ～！！$nあんなデカブツ、どうしようも――"
    },
    {
        "name": "",
        "message": "――山の向こうから顔を出したのは、$n天を衝くような体躯に、無数の触手をうごめかせた、$n信じられないほど巨大なマガツヒだった。"
    },
    {
        "name": "イズナ",
        "message": "くぅ……あんなのが出てくるなんて聞いとらんぞ！！$nこのままでは……犠牲者が……！"
    },
    {
        "name": "アスカ",
        "message": "イズナちゃん！$nあぶない！"
    },
    {
        "name": "イズナ&アスカ",
        "message": "うわあああああ！！！！"
    },
    {
        "name": "",
        "message": "イズナ！　アスカ！$n巨大な触手が二人を吹き飛ばし、$nはるか彼方に吹き飛ばしてしまう！"
    },
    {
        "name": "毘沙門天",
        "message": "あら、大変ねぇ"
    },
    {
        "name": "",
        "message": "この状況にもかかわらず、$n毘沙門天は相変わらず自然体で佇んでいるが……。"
    },
    {
        "name": "",
        "message": "しかし今回ばかりは……相手が悪すぎる！$n七福の力をもってしても、$n一人で太刀打ちできる大きさではない……！"
    },
    {
        "name": "毘沙門天",
        "message": "ふふ……知ったようなことを言って。$n本当に愚かな人の子ね……"
    },
    {
        "name": "マガツヒ",
        "message": "――――――！！！！"
    },
    {
        "name": "",
        "message": "ダメだ……！$n逃げろ毘沙門天……！"
    },
    {
        "name": "毘沙門天",
        "message": "心配無用よ。むしろこれくらいの方が――"
    },
    {
        "name": "毘沙門天",
        "message": "……？$n<name></name>君、何を……？"
    },
    {
        "name": "",
        "message": "……毘沙門天をとっさにかばったのはいいが、$n脚を触手に突き刺されてしまった……。$n血だまりがみるみる広がっていく……。"
    },
    {
        "name": "毘沙門天",
        "message": "何を馬鹿なことを……。$nわたしを助けてどうなるというの？"
    },
    {
        "name": "",
        "message": "……言ったはずだ。$n式神と陰陽師は一心同体。$n毘沙門天は、自分が守る。"
    },
    {
        "name": "毘沙門天",
        "message": "……まったく、またそんな世迷い言を。$n君のその血の量、軽傷ではないわよ？$n本当に、人の子は愚かだわ……"
    },
    {
        "name": "",
        "message": "返す言葉もない……。$nしかし、考える前に身体が$n動いてしまったのだから、仕方がない……。"
    },
    {
        "name": "毘沙門天",
        "message": "そんな曖昧な理由で飛び出したというの？$nそれでわたしが納得できるとでも……"
    },
    {
        "name": "毘沙門天",
        "message": "…………？$n私は今、怒りを感じているの……？$n自分には関係のないことなのに……？"
    },
    {
        "name": "弁財天",
        "message": "……あたしが死ぬのなんて怖くない。$nあたしは――"
    },
    {
        "name": "毘沙門天",
        "message": "…………"
    },
    {
        "name": "毘沙門天",
        "message": "……なるほど。$nそういうこともあるのね……。$n自分以外のことで感情が動かされる、と……"
    },
    {
        "name": "毘沙門天",
        "message": "まさかわたしが、こんな感情を持つなんて……$nこの器のせい、肉体持つモノの性かしら……？"
    },
    {
        "name": "毘沙門天",
        "message": "――ねえ、大丈夫？$n軽く処置はしたけれど、死にはしないわよね？"
    },
    {
        "name": "",
        "message": "……大丈夫だ。このくらいなんてことない。$n毘沙門天がいてくれれば、自分は死んだりしない。"
    },
    {
        "name": "毘沙門天",
        "message": "何の根拠もないくせに……$nずいぶんな大口ね、<name></name>君。$nふふ……本当に、おかしな子"
    },
    {
        "name": "毘沙門天",
        "message": "そうね……わたしがいる限り死なないと言うなら、$nもう君はこれから、もはや死ぬことはないわ"
    },
    {
        "name": "毘沙門天",
        "message": "わたしこそが不死身の災禍――$n“破壊”そのものが形をなした$n最悪の十二天なのだから"
    },
    {
        "name": "",
        "message": "そう言って彼女は、再びマガツヒに向かう。$n毘沙門天に触手が殺到し――"
    },
    {
        "name": "",
        "message": "――毘沙門天の右腕が、斬り飛ばされた。"
    },
    {
        "name": "毘沙門天",
        "message": "ふふ……そうよ……もっと来なさい……。$nこの肉の器を……"
    },
    {
        "name": "毘沙門天",
        "message": "壊し尽くしてっ……！！"
    },
    {
        "name": "",
        "message": "彼女の左腕が、脚が、触手に斬り刻まれていく……！$nしかし、彼女の顔に浮かんでいるのは、$n苦悶ではなく……高揚の笑み……！！"
    },
    {
        "name": "",
        "message": "彼女の傷口から……おぞましい何かが溢れ出す……！$n目を背けたくなるような闇が解き放たれ……$nそして……砲身の形を作っていく……！"
    },
    {
        "name": "毘沙門天",
        "message": "……ふふふっ。$nこの玩具は、わたしのもの。$n三下風情に……壊させはしないわぁ……！"
    },
    {
        "name": "毘沙門天",
        "message": "さぁ――失せなさい！！"
    },
    {
        "name": "毘沙門天",
        "message": "アッハハハハ――――！！！"
    },
    {
        "name": "マガツヒ",
        "message": "――――…………！！！！"
    },
    {
        "name": "",
        "message": "……彼女の一撃で、マガツヒは跡形もなく消滅した。$nい、今のは……一体……？"
    },
    {
        "name": "毘沙門天",
        "message": "ふふ。君は気にしなくていいわ。$nわたしの玩具は、何も知らないまま――"
    },
    {
        "name": "毘沙門天",
        "message": "日常を取り戻すのだから"
    },
    {
        "name": "",
        "message": "…………！！？$n毘沙門天の右腕が……胸に突き刺さった……！？$nしかし、不思議と痛みはない……。"
    },
    {
        "name": "",
        "message": "彼女が腕を引き抜くと、その手には$nいつか見たものと似たような符が握られていた。"
    },
    {
        "name": "毘沙門天",
        "message": "“いつだって心臓を預けている”なら……$nこんなもの、必要ないわよね"
    },
    {
        "name": "",
        "message": "そう言いつつ、彼女は符を引き裂いてしまう。$n何が何だかさっぱり分からない……。"
    },
    {
        "name": "イズナ",
        "message": "ごほっ……！　ごほっ……！$nおおい！　二人とも無事かあ～？"
    },
    {
        "name": "アスカ",
        "message": "あれ？　マガツヒ、$nどこに行っちゃったんスか？"
    },
    {
        "name": "毘沙門天",
        "message": "二人とも戻ってきたみたいね。$n立ちなさい、<name></name>君。$nそのままでは君、死んでしまうわよ？"
    },
    {
        "name": "毘沙門天",
        "message": "……安心して。手は貸してあげる。$nわたしたち……一心同体、なのだから。ふふ"
    },
    {
        "name": "",
        "message": "差し伸べられた手のひらを掴む。$nその手は……不思議とあたたかく、$n頼もしさに心が落ち着いたのだった……。"
    }
]