{
    "――年の瀬も近づき、街が華やぐクリスマス前。$nひょうりの様子を見に、彼女が統べる$n任侠団体『百夜組』の屋敷へやって来た。": "——年关将近，街上开始热闹起来的圣诞节前夕。我为了探望$n小桐，来到她统治的任侠团体「百夜组」的宅邸。",
    "ひょうりに代替わりした際には他の組との“抗争”も$nあったとはいえ、今ではすっかり平穏らしいが――": "虽然在小桐接任首领时，和其他帮派之间发生过「斗争」，不$n过现在似乎已经完全恢复平静——",
    "組員たち": "组员们",
    "てめえら！　たるんでんじゃねえぞ！$n気合い入れろ！　百夜組の総力戦じゃああああ！": "你们这些家伙！别松懈了！打起精神！这可是百夜组的总体战$n啊啊啊啊！",
    "全く平穏ではなかった！$n組員全員が巨大な刃物を背負って、$n爛々と目を輝かせている……！？": "完全不平静！所有组员都背着巨大的刀具，眼神闪闪发亮……$n！？",
    "ひょうり": "小桐",
    "――あら？　どうしたのよこんなところで": "——哎呀？怎么了，你在这里做什么？",
    "ひょうりの様子を見に来たのだが……。$nこ、これは何の騒ぎだろうか？$nまさか……こ、こう……": "我是来探望你的……这、这是在吵什么？难不成……是、是…$n…",
    "ふふふ……よく分かったわね。$nそのとおり。今、百夜組は組をあげて……": "呵呵呵……你真清楚。没错，现在百夜组正动员所有成员……",
    "“工作”に取り組んでいるのよ～～！": "在进行「工作」～～！",
    "……なる、ほど……！？": "……原来、如此……！？",
    "って、あれは巨大なクリスマスツリー？$nひょうりたちが作ったのだろうか？": "咦，那是巨大的圣诞树？是小桐和组员们做的吗？",
    "ふっふ～～ん。すごいでしょ。$n他にもご馳走と、う～～んっとおっきなケーキを、$nいっぱい作ってるんだからっ": "哼哼～～很厉害吧。我们还做了很多好吃的，还有～～超大的$n蛋糕！",
    "一体何のために……？$nクリスマスパーティーでも開くのだろうか？": "到底是为了什么……？难道要开圣诞派对吗？",
    "そうよ！　シマの子供たちを招待して、盛大にね！$n全ては、子供たちと仲良くなるため――$nね！　みんな！": "没错！要招待岛上的小孩，办一场盛大的派对！一切都是为了$n和孩子们打好关系——对吧！大家！",
    "うおおおおおおおおおおおおお！！！！": "唔哦哦哦哦哦哦哦哦哦哦哦哦哦！！！！",
    "すごい殺気……いや、やる気である！$n何がひょうりたちをここまで突き動かすのだろうか？": "好强烈的杀气……不，是斗志！到底是什么让小桐他们如此奋$n起？",
    "組員A": "组员A",
    "あ～、それはな……": "啊～～这个嘛……",
    "商店街にようこそお子さん方ぁ！$nおもちゃもたくさんありまっせぇ～～！": "欢迎来到商店街，小朋友们！这里有很多玩具哦～～！",
    "子供たち": "孩子们",
    "ふぇ～～ん！　顔、怖いよぉ～～！$n頬に十字傷だぁ！$n逆に刃がついた刀で頭をかち割られるぅ～～！": "呜哇～～！脸好可怕哦～～！$n脸颊有十字伤疤！$n会被刀子割破头～～！",
    "はぁ……。$nまさかあんなに怖がられちまうなんて。$n商店街の手伝いなんかするんじゃなかったなぁ……": "唉……$n没想到会吓到他们。$n早知道就不该来商店街帮忙……",
    "女組員A": "女组员A",
    "こちとら子供大好きなのによぉ……うぅぅっ！$nや、やるせねえぜぇ！　子供に好かれるような$nツラじゃねえってのは分かってるけどよぉ～～！": "我们明明很喜欢小孩……呜呜呜！$n好、好难过哦！虽然知道自己的脸不会受小孩欢迎～～！",
    "……たしかに。わたしもここの組長になる前は$nあなたたちのこと、ずっと怖かったわ……。$n特に顔が": "……的确。我在成为这里的组长之前，也一直很怕你们……尤$n其是脸。",
    "組員B": "组员B",
    "そ、そうだったんですかぁ！！？": "是、是这样吗！？",
    "でも今は違うわ！$nみんなが本当は優しいってこと、知ってるから！": "不过现在不一样了！$n我知道大家其实很温柔！",
    "子供たちだってきっと、本当のあなたたちを知れば、$n心を開いてくれるはずよ！　わたしが何とかして$nあげるから、どぉ～んと任せなさい！": "孩子们一定也是，只要知道你们真正的样子，就会打开心房！$n我一定会想办法让你们和孩子们好好相处，放心交给我吧！",
    "お、お嬢ぉぉぉぉぉ～～！$nそこまであっしらのことを思ってくれてたなんて……！$nうぅぅっ！　い、一生ついていきまさぁ～～！！": "大、大小姐～～～～！$n没想到您这么为我们着想……！$n呜呜呜！我、我一辈子都跟定您了～～！！",
    "――というわけで、シマの子供たちを招き、$nクリスマスパーティーという名の懇親会を$n開くことになったと……。": "——于是，我们邀请了岛上的孩子，举办了一场名为圣诞派对$n的联欢会……",
    "ええ……。$nただ、怖がっている相手がたくさんいる屋敷に、$n子供たちが来てくれるとは思えないのよねぇ……": "嗯……只是，我不认为孩子们会愿意来这栋有很多可怕大人的$n宅邸……",
    "……ならば、もっとお祭り感を出して、$n子供たちに来たいと思ってもらうのはどうだろうか。$n例えば……友達を呼んでにぎやかにしたり……。": "……既然如此，就营造出更热闹的气氛，让孩子们想来参加吧$n。比如说……找来朋友，让场面更热闹……",
    "それだぁ！": "就是这个！",
    "わぁぁぁぁ……！　$nこのクリスマスツリー、おっきくて、きれぇ～～～！": "哇啊啊啊啊……！$n这棵圣诞树好大，好漂亮～～！",
    "――百夜組に残ってひょうりを手伝い、$nようやく迎えたクリスマスパーティー当日。$n努力のかいあって、たくさんの子供たちが来てくれた。": "——我留在百夜组帮组长的忙，终于到了圣诞派对当天。努力$n有了回报，来了很多孩子。",
    "ふっふっふっ……$nこれも、組長たるわたしの伝手で、$n友達をたくさん呼べたお陰ね――": "呵呵呵……这都是多亏了我这个组长的人脉，找来了很多朋友$n——",
    "蜘蛛丸": "蜘蛛丸",
    "すっげー！　きらきらのぴっかぴかじゃねえか！$nこのご馳走も、好きなだけ食っていいんだよな！": "好棒哦！亮晶晶的耶！$n这些大餐，我们也可以尽量吃吧！",
    "夜叉丸": "夜叉丸",
    "意地汚いぞ蜘蛛丸。$nまずは私が、このとてもとても美味しそうな$nご馳走を全て毒見しよう……じゅるっ": "蜘蛛丸，你太贪心了。首先由我来试毒，尝尝这些看起来非常$n美味的餐点……（流口水）",
    "滝夜叉姫": "泷夜叉姬",
    "おーい、よだれが出ておるぞ夜叉丸ー。$nまあ、折角じゃ。$n誰が一番多く食えるか競うとするかのう": "喂～夜叉丸，口水流下来了哦～既然难得有这个机会，就来比$n比看谁能吃得最多吧。",
    "確かに、滝夜叉姫たちを呼んだのは正解だった。$nいやが上にもお祭り感が増している。": "找泷夜叉姬她们来果然是正确的决定。热闹的气氛更上一层楼$n。",
    "滝夜叉姫たちにはもう事情を話してあるので、$nあとは皆で協力して、百夜組と子供たちの$n親睦を深められれば――。": "我已经把事情告诉泷夜叉姬她们，接下来只要大家同心协力，$n让百夜组和孩子们加深感情——",
    "あわわわわわっ！$nなぜここに滝夜叉組がぁ……！？$nカ、カカカ、カチコミに来たのかぁ！？": "啊哇哇哇哇哇！为什么泷夜叉组会在这里……！？难、难难难$n、难道是来踢馆的吗！？",
    "し、しまった！$n肝心の組員たちに話すのを忘れていた……！": "糟、糟了！我忘记告诉组员们这件事了……！",
    "お、お、お嬢！　下がってくだせえ！$nこうなったら、刺し違えてでもお嬢を守ってやるぅ！": "大、大、大小姐！请您退后！事到如今，就算要同归于尽，我$n也要保护大小姐！",
    "ひょ、ひょわわ……！$nじんぎなきたたかいが始まっちゃうぅぅ！": "哇啊啊啊……！要开始一场腥风血雨的战争了！",
    "ちょっとちょっと！　子供たちが怖がってるでしょ！$nドスを引っ込めなさい！　そもそも滝夜叉姫さんたちを$n呼んだのはわたしなんだから！": "等一下！孩子们会害怕的！把刀收起来！再说，找泷夜叉姬她$n们来的就是我！",
    "お、お嬢が、滝夜叉組をっ？　な、なぜですかい！$n滝夜叉組はあっしら百夜組より勢力もうんと大きいし$n抗争になれば、ひとたまりもないでっせ！": "大、大小姐找泷夜叉组来？为、为什么！我们百夜组的势力比$n他们大很多，要是打起来，我们根本撑不住！",
    "抗争になんかならないわよっ。$nだってわたし、滝夜叉姫さんとはマブダチだし……$nみ、見ててよ～～": "不会打起来的。我和泷夜叉姬是死党……你、你们看～～",
    "え、えいやっ！": "嘿、嘿呀！",
    "あ、あんなにガッツリ肩を組んで怒られないだろうか？$n確かに二人は仲がいいが、それは任侠集団を率いる$n者同士の、先輩と後輩のような間柄だったはず……。": "这、这样紧紧勾着人家的肩膀，不会被骂吗？虽然她们感情的$n确很好，但那应该是率领任侠集团的人之间，类似前辈和后辈的关系……",
    "ふふ……そうじゃな。マブダチじゃ。$nお礼にと言っては何だが、$n今度はぜひ妾の組にも遊びに来るとよい": "呵呵……没错，是死党。作为回礼，下次你一定要来妾身的组$n里玩。",
    "うぉぉ～～。お嬢、すげえ……$n滝夜叉組に招待されてるぞ。$nいつの間にあんな大物と……": "哇啊啊～～大小姐好厉害……竟然被泷夜叉组邀请了。什么时$n候和那种大人物……",
    "ただ――$nふふっ。無事には帰さぬかもだがのぉ": "不过——呵呵，可能不会让你平安回去哦。",
    "なっ……！$nやっぱりお嬢のタマ取るつもりだ！$nお、おおおお、お嬢を守れぇ～～！！": "什么……！果然想夺走大小姐的贞操！保、保保保保、保护大$n小姐～～！！",
    "ふぇぇぇぇんん！！　こ、怖いよぉ～～！！$nホワイトクリスマスが真っ赤に染まっちゃうよぉぉ！": "呜哇啊啊啊啊！！好、好可怕～～！！白色圣诞节染成一片血$n红了！",
    "もう、滝夜叉姫さ～～ん。$nからかわないでよぉ～～": "真是的，泷夜叉姬～～不要这样捉弄我啦～～",
    "ふふふ、すまんすまん。$n可愛くて帰したくなくなってしまう……$nと言いたかっただけなのじゃよ": "呵呵呵，抱歉抱歉。只是因为$n太可爱，不想让你回去……想这样捉弄你罢了。",
    "まあ、安心するのじゃ。$n妾も、困っている後輩を$n手助けしに来たにすぎぬ": "好了，放心吧。$n妾身也只是来帮有困难的后辈一把。",
    "怖がらせてしまってすまなかったのぅ、よい子たち。$nお詫びの印にプレゼントを……$nほれ、妾の故郷のお菓子じゃ": "抱歉吓到你们了，好孩子。$n作为赔礼，送你们礼物……$n来，这是妾身故乡的点心。",
    "うわぁぁぁ、おいしそぉ～～！$nありがとう、お姉ちゃん！": "哇啊啊啊，看起来好好吃～～！$n谢谢你，大姐姐！",
    "さすがは滝夜叉姫……。$nもう子供たちの心を開かせてしまった。$n彼女に任せておけば全て上手く――": "不愧是泷夜叉姬……$n已经让孩子们敞开心房了。$n只要交给她，一切都会很顺利——",
    "さてと、お近づきにもなれたことじゃし、$n妾たちと一緒に“楽しいこと”をするとしようかのぅ。$nふっふっふっ……": "好了，既然已经混熟了，就和妾身等人一起做些「快乐的事」吧。$n呵呵呵……",
    "怖そうな笑みを浮かべている！？$nい、一体何をするつもりなのか――！？": "她露出可怕的笑容！？$n她、她到底想做什么——！？",
    "うりゃーーーー！$n爆走蜘蛛丸ソリの乗り心地はどうだぁ！？$n振り落とされんじゃね～～ぞぉ～～！": "喝啊————！$n这辆暴冲蜘蛛丸雪橇坐起来如何啊！？$n小心别被甩下去了～～！",
    "わ～～～い！　はやいはや～～い！！": "哇～～～！好快好快～～！！",
    "本当にただ楽しいことをし始めただけだった。$n言い方が紛らわしい……。": "真的只是开始做些开心的事而已。$n她的说法太容易让人误会了……",
    "滝夜叉姫さんたち、すごいわ！　$n子供たちの心をつかんでる！　負けてられないわ！$nわたしたちもソリで子供たちに楽しんでもらうわよ！": "泷夜叉姬她们好厉害！$n抓住了孩子们的心！不能输！$n我们也用雪橇让孩子们开心吧！",
    "へへ！　そう言うと思って、$nすげぇソリを作っておきやしたぜ！$n『噴流(ジェット)推進ソリ』です！": "嘿嘿！我就知道你会这么说，$n我做了很厉害的雪橇哦！$n叫做『喷射推进雪橇』！",
    "わぁ！　いいもの作ったじゃない！$nよ～～し……！": "哇！做得真好！$n好～～……！",
    "――みんなちゅうも～～くっ！$n百夜組のソリをお披露目するから見てなさい！": "——大家注意～～！$n百夜组的雪橇要亮相了！",
    "なになにぃ～？　どんなソリなの～～？": "什么什么～？是什么样的雪橇～～？",
    "それは……あ、これが説明書ね。$nえっと、ソリの後ろに取り付けた爆弾を起爆して、$nその威力で進む最高にかっこいいソリ――": "那是……啊，这是说明书。$n我看看，引爆装在雪橇后面的炸弹，$n利用爆炸的威力前进，是最帅的雪橇——",
    "――えぇぇぇ！？$nば、ばば、爆発させるのぉ……！？": "——咦咦咦咦！？$n要、要要、要爆炸吗……！？$n",
    "へい！$n火薬は調整してやすから！$nド派手にやっちゃってくだせえ！": "是的！$n火药已经调整好了！$n请尽情地爆炸吧！",
    "う、うぅぅ……怖いけど……$n子供たちと仲良くなるため……。$n頑張れ……頑張るのよ、わたし……っ": "呜、呜呜……虽然很可怕……$n但这是为了和孩子们打好关系……$n加油……我要加油……！",
    "よ～～し！　発っっし～～～ん！！": "好～～！发～～射～～！！",
    "次の瞬間、ひょうりの乗ったソリは$nすごい勢いで飛び出し……$nそのまま空へと飛び立っていった……": "下一瞬间，小灯骑的雪橇以惊人的速度飞了出去……然后直接$n飞上天空……",
    "きゃああああああああ！！$nほ、星になっちゃぅぅぅぅぅ！！": "呀啊啊啊啊啊啊啊啊！！$n要、要变成星星了～～～～！！",
    "お、お嬢～～～～！！": "大、大小姐～～～～！！",
    "ひぅぅぅぅっ！$nあんな昇天しちゃいそうなソリ、乗りたくなぁ～い！$nくもまるのソリがいいぃ～～！": "咿呜呜呜呜！$n我、我不要坐那种好像会升天的雪橇～～！$n我还是喜欢云丸的雪橇～～！",
    "いたたたた……。$nくぅぅ～～、どうして上手くいかないのぉ～": "好痛痛痛痛……$n呜～～为什么就是做不好～",
    "ふふ……滝夜叉組の方が$n親しみやすいということじゃのう": "呵呵……看来是泷夜叉组比较亲切呢。$n",
    "た、滝夜叉姫……！？$nそんな風に火をつけてしまっては――。": "泷、泷夜叉姬……！？$n你这样煽动她们的话——",
    "ぐぬぬぬっ！　上等じゃない！　こうなったら、$n百夜組と滝夜叉組！　どっちが子供たちと$nより仲良くなれるか、勝負よ！": "咕呜呜呜！谁怕谁！既然这样，$n百夜组和泷夜叉组！来比比看谁和孩子们比较要好！",
    "行くぞ、てめーら！": "你们几个，要上咯！",
    "うっしゃああああああ！！$n百夜組の底力、見せてやらああああ！！": "好啊啊啊啊啊啊！！$n让你们瞧瞧百夜组的潜力！！",
    "やはりか……。$n滝夜叉姫もこうなることくらい分かっていただろうに。": "果然……$n泷夜叉姬应该也料到事情会变成这样吧。",
    "だってこっちの方が楽しそうじゃも～～ん": "因为这样比较有趣嘛～～",
    "こうして、子供たちの人気をめぐって、$n仁義なきクリスマス抗争が幕を開けるのだった――。": "于是，为了争夺孩子们的支持，$n无情的圣诞战争就此拉开序幕——",
    "ふふっ。そんな遅い雪玉で、$nこの夜叉丸を仕留めようとは愚の骨頂。$nもっと素早く投げねば、かすりもしませんよ？": "呵呵。想用那么慢的雪球打倒我$n夜叉丸，简直愚蠢至极。$n不扔快一点的话，连边都擦不到哦？。",
    "お姉ちゃん速すぎるよぉ～～！$nうぅぅ～～！　絶対当ててやるぅ～～！": "姐姐你太快了啦～～！$n呜呜呜～～！我一定要打中～～！",
    "雪合戦とは考えたわね……！$nでも、こっちはもっと刺激的に行くわよ！": "竟然想到打雪仗……！$n不过，我们要玩得更刺激一点！",
    "子供たち！　こっちで一緒に“雪抗争”して$n遊びましょ！　あの怖い顔の人たちに$n思いっきり雪玉ぶつけちゃえ！": "孩子们！和我们一起玩$n“雪抗争”吧！用力朝那些可怕的人扔雪球！",
    "ゆ、雪抗争……？$nなんだかよくわかんないけど……え、えーい！": "雪、雪抗争……？$n虽然听不太懂……嘿、嘿～！",
    "ぐぼっ！　ぐえぇあああぁぁぁっ！$nはらにぃ……腹に雪玉、がぁ……！$nぐふっ……あっしらは先に逝くぜ……げぼあっ！": "咕噗！咕恶啊啊啊啊啊啊！$n肚……肚子……！$n咕呼……我们先走一步了……咳噗！",
    "ナイス迫真の演技よ！$nカタギじゃ味わえないこの刺激的な体験に、$nきっと子供たちも喜んでくれるはず――！": "好逼真的演技！$n这种一般老百姓无法体验的刺激感，$n孩子们一定也会喜欢的——！",
    "子供A": "小孩A",
    "ひ、ひぇぇぇぇん！$nわ、わたし、なんてことを……。$nこの歳で牢屋送りはやだよぉ！　うぇぇぇぇん！": "呜、呜哇啊啊啊啊！$n我、我做了什么坏事……$n我才不想这么小就进牢房！呜哇啊啊啊啊！",
    "子供B": "小孩B",
    "へへ……そう、かな……僕はなんだか……$nドキドキして……ハマりそうだよ……": "嘿嘿……是、是吗……我总觉得……$n有点兴奋……好像会上瘾……",
    "いや……変な扉が開いてしまっているではないか。$n情操教育に悪いから、やめた方がよいじゃろ": "不……这下子会打开奇怪的门吧。$n对情操教育不好，还是别玩了。",
    "うぅぅぅぅっ！　つ、次よ！　次！": "呜呜呜呜呜！下、下一个！下一个！",
    "どうだテメェら！　どでけえ雪玉の上に、$n雪で作った滝姐の顔をのっけた――$n滝姐雪だるまだ！": "怎么样！你们看！在超大的雪球上，$n放上用雪做成的泷姐的脸——$n泷姐雪人！",
    "二頭身になった妾、か……。$nめっちゃ気色悪いではないか……": "变成二头身的本宫吗……$n感觉好恶心……",
    "あははははっ！　面白～～い！！": "啊哈哈哈哈！好好玩～～！！",
    "くっ……！　わたしたちは、もっとすごいもの――$nわたしの雪像を作るわよ！　まずは雪をかき集めて！": "唔……！我们来堆更厉害的东西——$n来堆我的雪雕吧！先收集雪！",
    "うっす！　おい、やるぞてめぇら！": "收到！喂，你们几个，要上啦！",
    "……ん！？$n百鬼夜行がひょうりの後ろに……！？$n雪集めをこっそり手伝おうとしてるのか！？": "……嗯！？$n百鬼夜行在小乌龟后面……！？$n是想偷偷帮忙收集雪吗！？",
    "ふわぁぁぁん！　な、なにあれぇ～～！$nば、ばばば、バケモノだぁぁぁぁ～～！": "呜哇啊啊啊！那、那是什么～～！$n怪、怪怪怪、怪物啊啊啊啊～～！",
    "え、ええー！？$nなに！？　わ、わたしの顔が、$nバケモノみたいに怖いってこと～！？": "咦、咦咦——！？$n什么！？我、我的脸，$n像怪物一样可怕吗～！？",
    "ううぅぅ、そ、そんなぁ……$nぐすっ。そんなことない、のに……": "呜呜呜呜，怎、怎么会……$n呜呜。明明没有那种事……",
    "えっ……あ、えっと……ごめん……。$nお姉ちゃんはバケモノみたいじゃないよ": "咦……啊，呃……对不起……$n姐姐才不是怪物",
    "ほ、ほんとぉ……？": "真、真的吗……？",
    "うん、だから一緒に$n雪だるま作ってあそぼ？": "嗯，所以一起$n堆雪人玩吧？",
    "うん……！": "嗯……！",
    "いや、どっちが子供なのか……！？": "呃，到底谁才是小孩子啊……！？",
    "こうして、ひょうりたち百夜組もだんだんと$n子供たちと打ち解けてはきたのだが、$nやはり滝夜叉組の方が子供たちの心を掴んでおり――。": "就这样，我们百夜组也渐渐和孩子们打成一片，但还是泷夜叉$n组更受孩子们喜爱——",
    "ふっ……私のドス捌きをもってすれば、$n七面鳥を綺麗に切り分けるなど、$n造作もありません……": "呵……只要我挥舞这把刀，就能轻松地把火鸡切开……",
    "お姉ちゃん、すごいすご～～い！$nわたしにも、刀の使い方教えて～～！": "姐姐好厉害～～！也教我刀的用法吧～～！",
    "くぅぅ……このままだと、$n滝夜叉組と子供たちの親睦を深める$nパーティーになっちゃうぅぅ……": "呜呜……再这样下去，会变成泷夜叉组和孩子们加深感情的派$n对……",
    "こ、こうなったら――最終兵器よ！": "既、既然如此——就用最终兵器！",
    "女組員B": "女组员B",
    "お嬢……遅いな……。$nどこに何しに行ったんだ……？": "小姐……好慢啊……$n她去哪里了……？",
    "ま、ま、まま、待たせたわね……": "让、让、让、让你们久等了……",
    "ひょ、ひょうり！？$n何を持ってきて……そ、それは！": "百、百夜！？$n你拿什么来……那、那是！",
    "え、ええ。みんなでいくつも作った巨大ケーキよっ。$nお、重くて、一つしか運べなかったけど……$nこれで、子供たちも喜ぶはず……": "是、是啊，这是大家一起做的巨大蛋糕哦！$n虽、虽然因为太重，我只能搬一个……$n不过，孩子们应该会喜欢这个……",
    "ふぎゃ！？　だ、段差――ッ！？": "呜呀！？地、地板——！？$n",
    "あ、危ない……！": "危、危险……！",
    "お嬢～～～！！": "小姐～～～！！",
    "きゃああああああああ！！": "呀啊啊啊啊啊啊啊啊！！",
    "間に……合わなかった……。$n結局全員で、ひょうりがひっくり返した巨大ケーキを、$n頭からかぶってしまったのだった……。": "没……赶上……$n结果，所有人都被翻倒的巨大蛋糕……$n从头淋得满身……",
    "や、やっちゃったぁ～～～～！！$nみんなが一緒に作ってくれたケーキなのにぃぃ！": "搞、搞砸了～～～～！！$n明明是大家一起做的蛋糕～～！",
    "気にする必要はない。$nひょうりに怪我がないようでよかった。": "不用在意。$n幸好你没受伤。$n",
    "そうですぜ！　お嬢の安全が一番でやすから！$n巨大ケーキはまだまだあるんですし、$nそう落ち込まないでくだせえ！": "就是说啊！小姐的安全最重要！$n反正还有巨大蛋糕，$n请别那么沮丧！",
    "うん……。$nみんな……ありが……――": "嗯……$n大家……谢谢……",
    "ぷふっ。ふふふっ……ご、ごめんっ。$nみんな……顔中にクリームついてて、$n面白くって……ふふふっ": "噗噗！呵呵呵……抱、抱歉！$n大家……脸上都是鲜奶油，$n看起来好好玩……呵呵呵！",
    "えっ？　あっ、ほんとだ……。$nって、お嬢もクリームまみれじゃないですか！$nサンタの髭みたいになってますぜ！　はっはっはっ！": "咦？啊，真的耶……$n呃，小姐你自己不也满脸鲜奶油吗！$n变得像圣诞老人的胡子了！哈哈哈！",
    "ふふ……": "呵呵……",
    "ふふふふっ！　お姉ちゃんたち、変な顔～！": "呵呵呵呵！大姐姐们的脸好奇怪～！",
    "ひょうり＆組員たち": "百夜＆组员们",
    "…………": "…………",
    "へへ～。おひげみてぇだろぉ～～。$nそら！　お前さんたちにもつけてやるぞ！": "嘿嘿～很像胡子吧～～$n来！我也帮你们涂！",
    "あはは！　や～だよ～！": "啊哈哈！才～不要～！",
    "ふふふ♪　待て待てぇ～～っ。$n組長サンタからは逃げられないわよ～！": "呵呵呵♪站住站住～～$n你们逃不过组长圣诞老人的魔掌～！",
    "それからしばらくの間、$nひょうり率いる百夜組と子供たちの、$n仲睦まじい鬼ごっこは続くのだった……。": "之后好一段时间，$n百夜组在组长百夜的率领下，和孩子们继续玩着感情融洽的捉迷藏……",
    "今日はありがとー！ $nクリスマスパーティーとっても楽しかった！": "今天谢谢你们！$n圣诞派对真的好开心！",
    "僕、まだ帰りたくないな～～！": "我还不想回去呢～～！",
    "あんまり遅くまで遊んでると、$nサンタさん来てくれなくなるぞぉ～": "玩太晚的话，圣诞老公公就不会来咯～",
    "また遊んでやっから、いつでも来いよな！": "我随时欢迎你来玩哦！",
    "ふふっ、双方いい笑顔をしておる。$nどうやら、無事に目的は達成されたようじゃし、$n妾たちの仁義なき戦いも引き分けで幕引きじゃの": "呵呵，双方都露出灿烂的笑容。看来目的顺利达成，我们这场$n不讲仁义的战斗也以平手收场。",
    "<name></name>、滝夜叉姫さん……$n本当にありがとう。$n全部、みんなが協力してくれたお陰よ……": "<name></name>、泷夜叉姬……$n真的谢谢你们。$n这都是多亏大家的帮忙……",
    "いや、全てひょうりのお手柄だ。$n誰よりも組員たちのことを思い、$n誰よりも頑張っていた、ひょうりの……。": "不，这全是小百合的功劳。$n比任何人都关心帮众，比任何人都努力的小百合……",
    "そうかなぁ……えへへ……。$nうん……そうだといいなぁ……": "是吗……嘿嘿……$n嗯……但愿如此……",
    "そうして微笑んだひょうりの表情は、$nクリスマスに相応しく、$n幸せに満ち溢れていたのだった……。": "小百合露出微笑，她的表情充满幸福，与圣诞节十分相衬……"
}