{
    "――陰陽寮へと戻る道すがら。$n善如龍王の提案で、観光がてらの帰り道と$nなったものの……。": "——在返回阴阳寮的路上。在善如龙王的提议下，我们决定在$n回程的路上顺便观光……",
    "善如龍王": "善如龙王",
    "ふぅん……これがその社か。$n随分歩かされたが、ここも古いだけだな": "哦……这就是那间神社吗？虽然走了很久，但这里也只是很老$n旧而已。",
    "……相変わらず文句が絶えない。$nその割には、機嫌はそこまで悪くないようだし、$n龍王なりの楽しみ方なのだろうか。": "……她还是一样满口抱怨。不过，她的心情似乎没有很差，这$n大概是龙王享受的方式吧。",
    "つまらなそうに眺める彼女の横顔が目に入る。$n端正な顔立ちに、涼しげな瞳……。$nじっと見つめていると、彼女が振り返った。": "她一脸无趣地眺望着神社。我看着她的侧脸。她有着端正的五$n官，以及冷淡的眼眸……我目不转睛地盯着她，她便转过头来。",
    "ん？　どうした": "嗯？怎么了？",
    "はっと気づいて首を振った。$nいや……特には……。": "我回过神来，摇了摇头。不……没什么……",
    "ふふ……そうか": "呵呵……这样啊。",
    "そう言うと、善如龍王は$nこちらの腕をとって抱き込んでくる……！？$n彼女の胸元の感触に、体がカッと熱くなった。": "善如龙王说完，便搂住我的手臂……！？我感觉到她胸部的触$n感，身体瞬间发烫。",
    "どうした？$nやけに苦しそうな顔をしているではないか": "怎么了？你的表情看起来很难受。",
    "いや……と答えるのが精いっぱいだった。$n自分が顔を伏せると、$n彼女は微笑んでそのまま離れていった。": "我好不容易才挤出「不……」这个回答。我低下头，她便微笑$n着放开我。",
    "……ふむ、まもなく日も暮れよう。$n今日は宿をとるか": "……嗯，太阳就快下山了。今天就先找地方住吧。",
    "宿という言葉に、また体が熱くなってしまう。$nその様を、善如龍王は楽しげに見つめていた……。": "一听到「住」这个字，我的身体又开始发热。善如龙王开心地$n注视着我……",
    "教団との戦いの後、$n善如龍王が言った言葉……。": "与教团的战斗结束后，善如龙王说……",
    "天命を変えられぬというなら、$nおまえとの子をつくればいい": "既然无法改变天命，那就和你生孩子吧。",
    "その言葉が、ずっと頭から離れなかった。$n善如龍王のことを意識してしまい、$nいつも通りの受け答えができない。": "这句话一直在我脑中挥之不去。我满脑子都是善如龙王，无法$n像平常一样与她交谈。",
    "だが、善如龍王はいつもと変わらぬ様子だ。$n自分だけが、一方的に調子を乱してしまっている。": "然而，善如龙王却一如往常。只有我单方面地心慌意乱。",
    "女将": "老板娘",
    "お部屋は同じでよろしいですか？": "两位要住同一间房吗？",
    "いや、別々で頼む": "不，麻烦分开。",
    "えっ？　と声をあげかけ、$nそれをすんでのところで呑み込む。$nてっきり同じ部屋を取るものかと……。": "我差点惊呼出声，但又及时吞了回去。我还以为她会跟我住同$n一间房……",
    "…………ふふ": "…………呵呵。",
    "彼女はそんな自分の気持ちを見透かしたかのように、$nこちらの反応を見て楽しんでいる。$nもしかして自分は、からかわれているのだろうか……。": "她仿佛看穿了我的心思，正以我的反应为乐。难道我被她耍了$n……",
    "布団に入ってはみたものの、$n思い返すのは善如龍王のことばかり……。$nこのままでは頭がおかしくなってしまいそうだ……。": "我钻进被窝，但满脑子都是善如龙王……再这样下去，我恐怕$n会疯掉……",
    "その時だった。$n部屋の扉が開かれた。": "就在这时，房门被打开了。",
    "はっとして起き上がろうとするが、$nすぐに何者かが自分の布団に潜り込んできた。": "我惊醒过来，正想起身，却有人钻进我的被窝。",
    "ふふ……やはりおまえは、いい顔をする": "呵呵……你果然有张好脸。",
    "善如龍王……！？": "善如龙王……！？",
    "おまえがあんまりいい反応をするものでな。$nこの時間まで寝ていなかったところを見ると……": "你反应这么好，我就忍不住了。看你这么晚还没睡……",
    "そう言うと善如龍王はこちらの体に手を這わせた。$n彼女の白魚のような手が自分の胸板を撫でるだけで、$n痛いくらいに体が反応してしまう……！": "说完，善如龙王的手在我身上游移。她白皙如玉的手抚摸我的$n胸膛，我的身体就起了反应，甚至有点痛……！",
    "おまえ、こんなに敏感だったか？$nふっ、見ろ、ただ撫でただけなのに……": "你以前有这么敏感吗？$n呵，你看，我只是摸了摸而已……",
    "するり、と股の隙間に$n彼女の手が潜り込んできて、声が漏れる。": "她的手滑进双腿之间，我忍不住叫出声来。",
    "不躾にも大きくさせて……$nそんなに期待していたのか？": "竟然变得这么大……你这么期待吗？",
    "直接触れられていないにもかかわらず、$n何度も跳ね上がる自分の分身。$n恥ずかしさで泣きそうになった。": "明明没有直接碰触，分身却一跳一跳的。我羞得想哭。",
    "ふふふ……まったく、$nたまらないな、おまえは": "呵呵呵……受不了，你真是……",
    "そんなにしてほしいのなら、乞い願うがいい。$n自らを満足させてほしいとな": "这么想要的话，就求我啊。求我满足你。",
    "自分、は……。": "我……",
    "高鳴る鼓動に、痛いくらいに膨張した牡茎……$nもはや我慢の限界だった。$n龍王にしてもらいたい……お願いだ。": "心跳加速，阴茎胀得发痛……已经忍到极限了。拜托，让我成$n为龙王吧。",
    "ふ……ふふ": "呵……呵呵。",
    "よくできた": "做得好",
    "そのまま、彼女の手は$nこちらの服をゆっくり脱がしていくのだった……。": "她直接脱下我的衣服……",
    "どうした？$nやけに硬い表情をしているが……$n慣れぬ仕方に緊張したか？": "怎么了？$n你的表情很僵硬……$n是不习惯这种玩法，所以紧张了吗？",
    "命じられるまま窓辺に立ち、$n善如龍王の片脚を抱え上げると、$n彼女はからかうようにそう言った。": "我按照她的命令站在窗边，$n抱起善如龙王的一条腿，$n她便调侃似地这么说。",
    "たまにはこのような趣向も悪くはあるまい。$n床に伏せ、布団を被って粛々と致すなど、$n我の性には――": "偶尔玩玩这种花样也不错。$n跪在地上，盖着棉被默默办事，$n不符合我的性子——",
    "善如龍王の視線がこちらの股間に移った。$n言葉を止め、一瞬目を丸くした彼女は、$n勝ち誇ったように舌なめずりする。": "善如龙王的视线移向我的胯下。$n她停下话语，一瞬间睁大眼睛，$n然后得意地舔了舔嘴唇。",
    "いや……そうではなかったか。$nそのマラの猛り様……くふ……$nおまえも昂っているではないか、この好き者め": "不……不是这样吗？$n瞧你那根阳具的威猛模样……呵呵……$n你也兴奋起来了不是吗？你这好色之徒。",
    "彼女の言う通り、自分は緊張しているわけではない。$n焦らされ、我慢の限界に達していたために、$n逸る気持ちを抑えようとしていたのだ。": "她说得没错，我并不是在紧张。$n而是因为被吊胃口，已经忍耐到极限，$n所以才在压抑着急躁的心情。",
    "ふふ……良いぞ……それでこそだ。$n我と子を生そうというなら、$nそれくらいの気概がなくては困る": "呵呵……很好……就是要这样。$n既然要和我生子，$n没有这点气概可不行。",
    "彼女のひんやりした指先が肉茎に添えられ、$nそのまま潤んだ膣口に先端が導かれる。": "她冰凉的指尖扶着肉茎，$n就这样将前端引导至湿润的穴口。",
    "さぁ……来い、男を見せよ。$n我の奥へと突き入れ、思う存分腰を振り、$n熱い子種を注ぎ込むがよい……♪": "来吧……来吧，展现你的男子气概。$n刺进我的深处，尽情地摆动腰部，$n将滚烫的精种注入……♪",
    "んくぅぅぅっ……！？$nふあっ……ずいぶん威勢が良いな……んん……。$n少しばかり、焦らしすぎたか……ふふ……": "嗯咕呜呜呜……！？$n呼啊……气势真猛……嗯嗯……$n有点吊胃口吊过头了……呵呵……",
    "……気持ちを抑えようとする試みは潰え、$n気付けば一息に彼女を貫いていた。": "……我压抑情绪的尝试失败，$n回过神来，发现自己已经一口气贯穿了她。",
    "ふぅ……焦ってすぐに漏らしたりするなよ？$n我より先に達することなど許さぬ。$n子を生すなら、二人で同時に果てねばな？": "呼……可别因为焦急而马上泄了哦？$n不许比我先高潮。$n要生子的话，得两人同时高潮才行。$n",
    "「子を生す」という言葉が、さらに興奮を加速させる。$nしかし、自分だけが先に果てるわけにもいかない。$nもどかしさに耐えながら、腰を動かし始める。": "「生子」这个词，让我的兴奋更加高涨。$n但是，我可不能一个人先高潮。$n我强忍着焦躁，开始摆动腰部。",
    "ふぁっ……あっ……んううううっ……！$nくふぅっ……あぁ、そうだ……良いぞ……$nその調子だ……んぅっ……くはぁぁぁっ……": "呼啊……啊……嗯呜呜呜呜……！$n咕呼……啊啊，对了……很好……$n就是这样……嗯呜……咕哈啊啊啊……",
    "熱く潤んだ膣内の粘膜が肉棒に絡みついてくる。$nそれを引き剥がすようにしながら、$n入り口から奥へと肉棒を往復させていく。": "肉棒被炽热湿润的粘膜缠住。$n我一边将它剥离，$n一边让肉棒在入口到深处之间往返。",
    "あぁ……おまえの、硬いものが……$n我の深くを、抉ってくる……んううっ……$nもっと、おまえの欲を、さらけ出せっ……！": "啊啊……你那硬物……$n在我的深处，挖来挖去……嗯呜呜……$n再更进一步，展现出你的欲望……！",
    "善如龍王の煽りに、昂りは増していく。$nその勢いのままに思い切り腰を振り、$n彼女の最奥を突き上げる。": "善如龙王的煽动，让我的兴奋更上一层楼。$n我顺着这股气势，尽情地摆动腰部，$n撞击她的最深处。",
    "熱くぬめった膣内が肉棒を根元まで包み込み、$n気を抜けばすぐに果ててしまいそうだ。$nしかし、少しでも動きを緩めると――。": "炽热湿润的穴内将肉棒包覆至根部，$n感觉只要稍有松懈，马上就会射精。$n但是，只要动作稍有放缓——",
    "んんっ……どうした、動きが鈍いではないか。$nそんなことでは、我を果てさせることはできぬぞ。$nほれ、もっとだ……もっと来ぬか……んふぅっ……": "嗯嗯……怎么了，动作很迟钝啊。$n这样可无法让我高潮哦。$n来，再激烈点……再激烈点……嗯呼……",
    "善如龍王は笑みを浮かべてさらに煽ってくる。$nこちらに余裕が無いのをお見通しの上で……。": "善如龙王露出笑容，进一步煽动我。$n她看穿了我已没有余裕……",
    "先に果てるわけにはいかないが、応えないわけにも$nいかない。限界を超えない際の際まで腰を振り、$n彼女を責めていく。": "虽然不能先高潮，但也不能不回应她。我将腰部摆动到极限，$n不断进攻她的最深处。",
    "ひうっ、んんんんんぅっ……！？　ふあっ、あっ……$nんふぅっ……そう、だ……良いぞ……その調子だ……$nはぁぁぁっ……やれば出来るではないか……ふふ……": "咿呜、嗯嗯嗯嗯嗯……！？呼啊、啊……嗯呼……对，就是这$n样……很好……就是这样……哈啊啊啊……只要有心就做得到嘛……呵呵……",
    "どれ、褒美をやろう……我の方からも動いてやる。$nおまえに、極上の快楽を味わわせてやろう……♡": "来，给你奖励……我也来动一动。$n让你品尝极致的快乐……♡",
    "善如龍王の尻尾が腰に巻き付いてくる。$n密着度が高まったその状態で、$n彼女は自分から腰を動かし始めた。": "善如龙王的尾巴缠住我的腰。$n在紧密贴合的状态下，$n她开始主动摆动腰部。",
    "んんっ、くっ、ふあっ……んふぅっ……！$nどうした……もうビクビクしているぞ？$nもっと、締め付けてやる……んっ、あはぁっ……！": "嗯嗯、咕、呼啊……嗯呼……！$n怎么了……你已经在发抖了哦？$n我再把你夹紧一点……嗯、啊哈……！",
    "自分の動きとは違う拍子に与えられる刺激に、$n思わず声が漏れそうになる。$n快感が全身に広がり、背筋がゾクゾクと震える。": "与自己动作不同的刺激，让我不禁差点叫出声来。$n快感扩散至全身，背脊阵阵发抖。",
    "こちらの反応に善如龍王は笑みを深くして、$nどこか嬉しそうに囁きかけてくる。": "我的反应让善如龙王加深笑意，$n她开心地对我低语。",
    "どうした？　そんなものか……？$n限界まで我慢した、濃ゆい子種でなければ、$n我を孕ませるなど到底できぬぞ？　くす……": "怎么了？就这点程度吗……？$n如果不是忍耐到极限的浓厚精种，$n是无法让我怀孕的哦？呵呵……",
    "絶え間ない快感で明滅する意識に、$n「孕ませる」という言葉だけがくっきり刻まれていく。": "在不间断的快感下闪烁的意识中，$n「怀孕」这个词深深烙印在脑海里。",
    "しっかりと善如龍王の脚を抱え直し、$n彼女の動きに合わせるようにして、$n最奥目がけて勢いよく肉棒を突き込んだ。": "我重新抱紧善如龙王的双腿，$n配合她的动作，$n朝最深处猛烈挺进肉棒。",
    "くふぅっん……はぁっ、あっ……これはぁ……！$nい、いつもと違うところに当たって……んああっ……$nたまらぬっ……ああっ、んはぁぁぁぁっ……！": "咕呼……哈啊、啊……这是……！$n撞、撞到跟平常不一样的地方……嗯啊啊……$n受不了了……啊啊、嗯哈啊啊啊啊……！",
    "善如龍王が、これまでとは違う反応を見せる。$n常に纏っていた余裕のある雰囲気が薄れ、$n快感に酔い始めているようだ。": "善如龙王的反应跟之前不同。$n她身上那股从容的氛围逐渐淡去，$n似乎开始沉醉于快感之中。",
    "ひうっ、んんっ……くぅぅぅっ……はぁぁぁぁっ……！$nもっとだ……我を孕ませたくば、もっと深く……子袋を$n突き上げるがよいっ……！　はぁっ、んふぅぅっ……♡": "咿呜、嗯嗯……咕呜呜呜……哈啊啊啊啊……！$n再来……想让我怀孕的话，就再深一点……$n朝子宫……！哈啊、嗯呼呜呜……♡",
    "彼女の甘い声が辺りに響く。$n窓の向こう、遠く宵闇を透かして、$n人影のようなものもちらほらと見える。": "她的娇喘声响彻四周。$n窗户的另一侧，透过遥远的夜色，$n隐约能看见人影。",
    "気付かれるのでは……と頭をもたげた理性を、$n善如龍王は目ざとく見逃さなかった。$nこちらの顎に手をやって婉然と微笑む。": "会被发现的……$n善如龙王眼尖地发现我脑中浮现的理性。$n她伸手托住我的下巴，嫣然一笑。",
    "んふ、何を恥じる？$n我は構わぬ……見せつけてやれ……。$nおまえが我のつがいだとな……んっ、ちゅうぅっ……！": "嗯呼，有什么好害羞的？$n我不介意……就让他们看个清楚……$n你是我伴侣的事实……嗯、啾呜呜……！",
    "――不意に唇を奪われた。$nたっぷりの唾液に濡れた熱い舌をねじ込まれ、$n舌の裏まで丁寧に舐め回される。": "——嘴唇突然被她堵住。$n她将沾满唾液的温热舌头伸进我嘴里，$n仔细地舔舐我的舌头内侧。",
    "くちゅっ、りゅぷっ、ちゅるぅっ、んっ……ぷはぁ……$nあぁ、旨いな……悪くない……。ヒトのやり方も、$n存外昂るではないか……んっ、ちゅむぅぅぅっ……！": "咕啾、噜噗、啾噜、嗯……噗哈……$n啊啊，真美味……还不坏……人类的做爱方式，$n也挺让人兴奋的嘛……嗯、啾呜呜呜……！",
    "善如龍王がこんな真似をしてくるとは……。$nそんな驚きは甘美な刺激に押し流され、$n心も身体も一気にとろけてしまう。": "善如龙王竟然会这么做……$n这股惊讶被甜美的刺激冲走，$n身心一口气融化。",
    "……ぷぁぁ……くふっ、興が乗った……。$n許す……そのいきり立ったマラで、$n我を一匹の雌にするがよいっ……♡": "……噗啊啊……咕呼、来劲了……$n我允许你……用那根耸立的肉棒，$n让我成为一只雌性……♡",
    "挑発的な眼差しに、できるかと問われている気がした。$n当然だ。善如龍王を自分の女にしてみせる……！": "她挑衅的眼神仿佛在问「你办得到吗？」。当然，我一定会让$n善如龙王成为我的女人……！",
    "くぅっん、ふあっ、あああっ……！$nんんっ……疼く……我の子袋が……$nおまえの子種を、求めているっ………はぁぁぁっ♡": "咕呜、呼啊、啊啊啊……！嗯嗯……好痒……我的子宫……在$n渴求你的精子……哈啊啊啊♡",
    "善如龍王が激しく腰を揺らすたび、$n濡れそぼった膣襞に$n肉棒が扱かれ、舐られ、翻弄される。": "善如龙王激烈地扭腰，肉棒在湿透的肉穴中被来回舔舐、翻搅。$n",
    "ま、まだ、出してはならんぞ……くっ、んんぅっ……$n我が許すまで、我慢しろ……はぁぁっ……$n出す時は、一番深くで、受け止めてやる……！": "还、还不能射出来……咕、嗯嗯……在我允许之前，你得忍住……哈啊啊……$n射精的时候，我会让你射在最深处……！",
    "正直、こちらも限界まで来ている。$n今すぐにでも、最奥目がけて射精したい。$nしかし彼女の命に従って必死に踏みとどまる。": "老实说，我也快到极限了。$n好想立刻朝最深处射精。$n但我遵从她的命令，拼命忍耐。",
    "んううっ……体が、勝手に動いて……$nおまえを、求めてしまうっ……！$nだが……いいっ、よいぞっ、ふああぁっ！": "嗯呜呜……身体擅自动了起来……$n在渴求你……！$n不过……很好，很好，呼啊啊啊！",
    "彼女の疼きはこちらにも伝わってくる。$nだからこそ、それに応えるため、$n膣奥をゴツゴツと突き上げていく。": "她的痒感也传给了我。$n所以我为了回应她，$n不断朝肉穴深处顶去。",
    "喘ぎと共に動く下腹……彼女の胎内。$n自分たちの証をここに残すために――。": "下腹随着娇喘扭动……她的子宫。$n为了在这里留下我们的证明——",
    "ひあっ、あぁぁぁっ……来る……果てるっ……！$n出せっ、子種っ……我の膣内にっ……！ $nあっ、はぁぁっ、ひぁあっ――": "咿啊、啊啊啊啊……来了……要去了……！$n射吧，精子……射在我的里面……！$n啊、哈啊啊、咿啊啊——",
    "――んあああああああっ……！！": "——嗯啊啊啊啊啊啊啊……！！",
    "ついに善如龍王が全身を震わせる。$nうねるように締めつけてくる膣内にせがまれるまま、$n彼女の最奥へ熱い精液を注ぎ込んだ。": "善如龙王全身颤抖。我在她蠕动的肉穴中，将炙热的精液注入$n她的最深处。",
    "くぅぅぅっ……ふあぁっ……感じる、ぞ……んぅっ……$n我の子袋に注がれた、おまえの熱い子種を……♡$nまずは一人目……といったところか……ふふ……": "咕呜呜呜……呼啊啊……我感受到了……嗯呜……$n你那注入我子宫的炙热种子……♡$n第一个……就是你了……呵呵……",
    "うまくいくだろうか……？$nもちろんそうなってほしい気持ちはあるが……。": "会顺利吗……？$n我当然希望会……",
    "なに、今回は失敗だったとしても、$n機会ならこの先いくらでもある。$n繰り返せば良い……何度でも、な……♡": "不过，就算这次失败了，$n今后还有机会。$n只要重复就好了……不管几次都行……♡",
    "そう言うと、彼女はぐっと顔を寄せてきた。$n思わず、彼女の瞳に吸い込まれそうになる。": "说完，她将脸凑了过来。$n我差点被她的眼睛吸了进去。",
    "……これほど愛でてやりたいと、$nヒトの子相手に思う日が来るとはな……。$nおまえは、面白いやつだ……んっ、ちゅっ……♡": "……没想到我竟然会对人类的孩子，$n产生这么强烈的爱意……$n你真是个有趣的家伙……嗯、啾……♡",
    "口づけをしながら、突飛な考えが浮かんだ。$n彼女の大それた望みも、もしかすると$n本当に叶ってしまうかもしれない……と。": "我一边亲吻她，一边冒出一个想法。$n她的愿望或许真的会实现……",
    "龍の熱い舌に囚われた自分は、$nもう身も心も、彼女に捧げてしまっている――。": "被龙的舌头缠住的我，$n身心都献给了她——"
}