{
    "アスカ": "飞鸟",
    "あわわわ……ヤバイっス……$nこのままじゃやられちゃうっス……": "啊哇哇哇……不妙……$n这样下去会被干掉的……",
    "イズナ": "伊尔娜",
    "うわああああ！！$nもうダメだああああ！！！！$nおしまいだああああ！！！！": "呜哇啊啊啊啊！！$n已经不行了啊啊啊啊！！！！$n完蛋了啊啊啊啊！！！！",
    "少女": "少女",
    "う、ううん……ここは……": "唔、唔唔……这里是……",
    "マガツヒ": "灾祸之日",
    "――――！！！！": "――――！！！！",
    "…………！！": "…………！！",
    " ": " ",
    "目を覚ました少女は$nこちらに向き直り、手を差し出す。": "醒来的少女$n重新面向这边，伸出手。",
    "手を……！": "手……！",
    "この絶体絶命の時に$nなにをやっておるのだああ！！！！": "在这种生死关头$n你还在干什么啊啊！！！！",
    "もうダメっスうううう！！$nつぶされちゃうううう！！！！": "已经不行了！！$n要被压扁了！！！！",
    "お願い……！　私の手を取って……！！": "求求你……！握住我的手……！！"
}